LICENSE.txt
MANIFEST.in
README.md
setup.cfg
setup.py
chailie/__init__.py
chailie/chailie.pyd
chailie.egg-info/PKG-INFO
chailie.egg-info/SOURCES.txt
chailie.egg-info/dependency_links.txt
chailie.egg-info/top_level.txt
chailie/Function/__init__.py
chailie/Function/optionDb.pyd
chailie/Ui/__init__.py
chailie/Ui/chailieUi.pyd
chailie/database/__init__.py
chailie/database/userOption.db